pysimilar/__init__.py
pysimilar-0.5.dist-info/LICENSE
pysimilar-0.5.dist-info/METADATA
pysimilar-0.5.dist-info/WHEEL
pysimilar-0.5.dist-info/top_level.txt
pysimilar-0.5.dist-info/RECORD
