Metadata-Version: 2.1
Name: pysimilar
Version: 0.5
Summary: A very light python libary for comparing similarity between text/strings
Home-page: https://github.com/Kalebu/pysimilar
Author: Jordan Kalebu
Author-email: isaackeinstein@gmail.com
License: MIT
Download-URL: https://github.com/Kalebu/pysimilar/archive/0.2.tar.gz
Keywords: pysimilar,python-plagiarism-library,natural language processing,NLP libary,python-tanzania
Platform: UNKNOWN
Classifier: Development Status :: 3 - Alpha
Classifier: Intended Audience :: Developers
Classifier: Topic :: Software Development :: Build Tools
Classifier: License :: OSI Approved :: MIT License
Classifier: Programming Language :: Python :: 3.6
Classifier: Programming Language :: Python :: 3.7
Classifier: Programming Language :: Python :: 3.8
Classifier: Programming Language :: Python :: 3.9
Requires-Python: >=3.6
Requires-Dist: scikit-learn
